api/__init__.py
api/__main__.py
api/wrapper_api.log
api/wrapper_api.py
simple_wrapper_api-0.2.0.dist-info/entry_points.txt
simple_wrapper_api-0.2.0.dist-info/WHEEL
simple_wrapper_api-0.2.0.dist-info/METADATA
simple_wrapper_api-0.2.0.dist-info/RECORD
